maybe/__init__.py
maybe/maybe.py
maybe_else-0.2.1.dist-info/LICENSE
maybe_else-0.2.1.dist-info/METADATA
maybe_else-0.2.1.dist-info/WHEEL
maybe_else-0.2.1.dist-info/top_level.txt
maybe_else-0.2.1.dist-info/RECORD
