Metadata-Version: 2.1
Name: maybe-else
Version: 0.2.1
Summary: Provides a Maybe class as a Python implementation of null-aware operators.
Home-page: https://github.com/matthewgdv/maybe
Author: Matt GdV
Author-email: matthewgdv@gmail.com
License: MIT
Platform: UNKNOWN
Classifier: Development Status :: 3 - Alpha
Classifier: Intended Audience :: Developers
Classifier: Programming Language :: Python :: 3.7
